flattr/mypy.py
flattr/py.typed
flattr/__init__.py
flattr/_fb_attrs.py
flattr/cflattr/encode.pyx
flattr/cflattr/builder.cpython-311-x86_64-linux-gnu.so
flattr/cflattr/number_types.pxd
flattr/cflattr/builder.pyx
flattr/cflattr/number_types.pyx
flattr/cflattr/number_types.cpython-311-x86_64-linux-gnu.so
flattr/cflattr/encode.cpython-311-x86_64-linux-gnu.so
flattr/cflattr/__init__.py
flattrs-0.1.16.dist-info/RECORD
flattrs-0.1.16.dist-info/WHEEL
flattrs-0.1.16.dist-info/top_level.txt
flattrs-0.1.16.dist-info/METADATA
flattrs-0.1.16.dist-info/LICENSE
