Metadata-Version: 2.1
Name: flattrs
Version: 0.1.16
License: MIT license
License-File: LICENSE
Requires-Dist: attrs
Requires-Dist: flatbuffers (==23.1.4)
Requires-Dist: numpy
Provides-Extra: dev
Requires-Dist: pytest ; extra == 'dev'
Requires-Dist: hypothesis (==6.61.0) ; extra == 'dev'
Requires-Dist: cython (==0.29.32) ; extra == 'dev'
Requires-Dist: coverage ; extra == 'dev'
Requires-Dist: tox (==4.0.11) ; extra == 'dev'
